AUTHORS
MANIFEST.in
README.rst
setup.py
cache_tools/__init__.py
cache_tools/models.py
cache_tools/tools.py
cache_tools/templatetags/__init__.py
cache_tools/templatetags/get_group_key.py
cache_tools/tests/__init__.py
cache_tools/tests/test_keyable_model.py
cache_tools/tests/test_tools.py
django_cache_tools.egg-info/PKG-INFO
django_cache_tools.egg-info/SOURCES.txt
django_cache_tools.egg-info/dependency_links.txt
django_cache_tools.egg-info/not-zip-safe
django_cache_tools.egg-info/top_level.txt